{
  "file_id": "1000076471",
  "raw_text": "=== CUSTOMER INFORMATION ===\nName :: BABY REYANSH SHARMA\nAddress :: Hoodi\nName :: BABY REYANSH SHARMA\n\n=== SUPPLIER INFORMATION ===\nRegd. Off.: Manipal Hospitals Private Limited\n(Formerly Columbia Asia Hospitals Private Limited)\nCIN: U85110KA2003PTC033055\nRegd. Off. The Annexe, #98/2, Rustom Bagh, HAL Airport Road, Bengaluru 560 017, Karnataka\nCITY: Bengaluru\nSTATE: Karnataka\nZIP_CODE: 560 017,\nNAME: Manipal Hospitals Private Limited\nADDRESS_BLOCK: Bengaluru 560 017, Karnataka\nADDRESS: Manipal Hospital Varthur Road\nSurvey No. 10P & 12P, Ramagondanahalli Village, Varthur Hobli, Whitefield, East Taluk, Bengaluru 560 066, Karnataka\nCITY: Bengaluru\nSTATE: Karnataka\nZIP_CODE: 560 066,\nNAME: Manipal Hospital Varthur Road\nADDRESS_BLOCK: Bengaluru 560 066, Karnataka\nNAME: manipalhospitals\nRegd. Off.: Manipal Hospitals Private Limited\n(Formerly Columbia Asia Hospitals Private Limited)\nCIN: U85110KA2003PTC033055\nRegd. Off. The Annexe, #98/2, Rustom Bagh, HAL Airport Road, Bengaluru 560 017, Karnataka\nVENDOR_ADDRESS: Manipal Hospital Varthur Road\nSurvey No. 10P & 12P, Ramagondanahalli Village, Varthur Hobli, Whitefield, East Taluk, Bengaluru 560 066, Karnataka\nVENDOR_NAME: Manipal Hospitals Private Limited\nVENDOR_NAME: Manipal Hospital Varthur Road\nVENDOR_NAME: manipalhospitals\nP: +91 33 6600 3300\nP: +91 80 4936 0300\nVENDOR_PHONE: +91 33 4099 8899\nVENDOR_URL: www.manipalhospitals.com\n\n=== ADDITIONAL DOCUMENT DETAILS ===\n\nAmount Paid: 4450.00 Amt. Adjusted: 4450.00 Bill Date :: 26/05/2025 Bill No :: MVB25OCS0046908 CIN:: U85110KA2003PTC033055 Total: 4450.00 Receipt Amt.: 4450.00 Total: 4450.00 Hospital No :: MH010295215 OPD No :: 012000687064 OPD Date :: 26/05/2025 Age/ Sex :: 5/Male Department :: PAEDIATRICS MVB Doctor :: Dr Anand Patil Sr No: 1 Mode: Online Payment Particulars: No. ************4779 dated: 26/05/2025. Generated/Printed By: (Mahesh) NOTE:: ONE FOLLOW UP VISIT WITH THE SAME DOCTOR WITHIN 3 DAYS WILL NOT BE CHARGED. E: info@manipalhospitals.com S.No.: 1 Particulars: CRP- QUANTITATIVE Unit: 1 Price: 1000.00 SAC: 999316 Amount: 1000.00  | S.No.: 2 Particulars: LIVER FUNCTION TEST Unit: 1 Price: 1800.00 SAC: 999316 Amount: 1800.00  | S.No.: 3 Particulars: URINE ROUTINE AND\nMICROSCOPY ( QUALITATIVE\nMETHOD) Unit: 1 Price: 450.00 Amount: 450.00  | S.No.: 4 Particulars: COMPLETE BLOOD COUNTS\n(AUTOMATED) Unit: 1 Price: 700.00 SAC: 999316 Amount: 700.00  | S.No.: 5 Particulars: DENGUE PROFILE IGG IGM NS1\n(RAPID TEST) Unit: 1 Price: 500.00 Amount: 500.00  | \n\nRaw Text Content:\n7:54\nVo\n5G\nLTE\n88\nMH010295215-MVB25OCS0\nL\nmanipalhospitals\nLIFE'S ON\nBILL OF SUPPLY\nHospital No\n: MH010295215\nOPD No\n: 012000687064\nName\n:\nBABY REYANSH SHARMA\nOPD Date\n: 26/05/2025\nAge/ Sex\n: 5/Male\nBill No\n: MVB25OCS0046908\nAddress\n: Hoodi\nBill Date\n:\n26/05/2025 12:07PM\nDepartment\n:\nPAEDIATRICS MVB\nDoctor\n:\nDr Anand Patil\nS.No.\nParticulars\nUnit\nPrice\nSAC\nAmount\n1\nCRP- QUANTITATIVE\n1\n1000.00\n999316\n1000.00\n2\nLIVER FUNCTION TEST\n1\n1800.00\n999316\n1800.00\n3\nURINE ROUTINE AND\n1\n450.00\n450.00\nMICROSCOPY ( QUALITATIVE\nMETHOD)\n4\nCOMPLETE BLOOD COUNTS\n1\n700.00\n999316\n700.00\n(AUTOMATED)\n5\nDENGUE PROFILE IGG IGM NS1\n1\n500.00\n500.00\n(RAPID TEST)\nTotal\n4450.00\nAmount Paid\n4450.00\n(Received with thanks a sum of Rupees Four Thousand Four Hundred Fifty only)\nPayment Details\nSr No\nMode\nParticulars\nReceipt Amt.\nAmt. Adjusted\n1\nOnline Payment\nNo. ************4779\n4450.00\n4450.00\ndated 26/05/2025.\nTotal\n4450.00\nGenerated/Printed By\n(Mahesh)\nNOTE: ONE FOLLOW UP VISIT WITH THE SAME DOCTOR WITHIN 3 DAYS WILL NOT BE CHARGED.\nManipal Hospital Varthur Road\nSurvey No. 10P & 12P, Ramagondanahalli Village, Varthur Hobli, Whitefield, East Taluk, Bengaluru 560 066, Karnataka\nP +91 33 6600 3300 / +91 33 4099 8899\nManipal Hospitals Private Limited\n(Formerly Columbia Asia Hospitals Private Limited)\nCIN: U85110KA2003PTC033055\nRegd. Off. The Annexe, #98/2, Rustom Bagh, HAL Airport Road, Bengaluru 560 017, Karnataka\nP +91 80 4936 0300 E info@manipalhospitals.com www.manipalhospitals.com",
  "gold": {
    "invoice_number": "MVB25OCS0046908",
    "patient_name": "BABY REYANSH SHARMA",
    "services": [
      {
        "service": "CRP- QUANTITATIVE",
        "amount": 1000,
        "quantity": 1,
        "department": "laboratory",
        "unit": 1,
        "mrp": 1000,
        "cgst": 0,
        "cgst_type": null,
        "sgst": 0,
        "sgst_type": null,
        "gst": 0,
        "gst_type": null
      },
      {
        "service": "LIVER FUNCTION TEST",
        "amount": 1800,
        "quantity": 1,
        "department": "laboratory",
        "unit": 1,
        "mrp": 1800,
        "cgst": 0,
        "cgst_type": null,
        "sgst": 0,
        "sgst_type": null,
        "gst": 0,
        "gst_type": null
      },
      {
        "service": "URINE ROUTINE AND MICROSCOPY ( QUALITATIVE METHOD)",
        "amount": 450,
        "quantity": 1,
        "department": "laboratory",
        "unit": 1,
        "mrp": 450,
        "cgst": 0,
        "cgst_type": null,
        "sgst": 0,
        "sgst_type": null,
        "gst": 0,
        "gst_type": null
      },
      {
        "service": "COMPLETE BLOOD COUNTS (AUTOMATED)",
        "amount": 700,
        "quantity": 1,
        "department": "laboratory",
        "unit": 1,
        "mrp": 700,
        "cgst": 0,
        "cgst_type": null,
        "sgst": 0,
        "sgst_type": null,
        "gst": 0,
        "gst_type": null
      },
      {
        "service": "DENGUE PROFILE IGG IGM NS1 (RAPID TEST)",
        "amount": 500,
        "quantity": 1,
        "department": "laboratory",
        "unit": 1,
        "mrp": 500,
        "cgst": 0,
        "cgst_type": null,
        "sgst": 0,
        "sgst_type": null,
        "gst": 0,
        "gst_type": null
      }
    ],
    "total_amount": 4450,
    "doctor_name": "Dr Anand Patil",
    "facility": "Manipal Hospitals Private Limited (Formerly Columbia Asia Hospitals Private Limited) Manipal Hospital Varthur Road Survey No. 10P & 12P, Ramagondanahalli Village, Varthur Hobli, Whitefield, East Taluk, Bengaluru 560 066, Karnataka P +91 33 6600 3300 / +91 33 4099 8899",
    "invoice_date": "26/05/2025 12:07PM",
    "payment_mode": "Online Payment",
    "patient_age": "5 years",
    "patient_gender": "Male",
    "patient_contact": null,
    "cgst": 0,
    "cgst_type": null,
    "sgst": 0,
    "sgst_type": null,
    "gst": 0,
    "gst_type": null,
    "discount": 0,
    "mrp": 4450,
    "round_off": 0
  }
}