{
  "file_id": "1000991300",
  "raw_text": "=== CUSTOMER INFORMATION ===\nNAME: Suresh Saini\nRECEIVER_NAME: Suresh Saini\n\n=== SUPPLIER INFORMATION ===\nADDRESS: FIT 'N' FLY [ Physiotherapy & Fitness]\n4/164, SFS, Near B2B , Shipra Path, Mansarovar, Phone:\nJaipur Email:\nSTREET: 4/164, SFS, Near B2B , Shipra Path, Mansarovar,\nCITY: Jaipur\nNAME: FIT 'N' FLY [ Physiotherapy & Fitness]\nADDRESS_BLOCK: 4/164, SFS, Near B2B , Shipra Path, Mansarovar,\nJaipur\nADDRESS: Fly\n'N'\nFit\nCentre\n& Fitness JPR\nPhysiotherapy Mansarovar,\n4/164, S SFS, Near\nSTREET: Physiotherapy\n4/164, S SFS, Near\nADDRESS_BLOCK: Physiotherapy\n4/164, S SFS, Near\nNAME: Fit N.Fly\nVENDOR_ADDRESS: FIT 'N' FLY [ Physiotherapy & Fitness]\n4/164, SFS, Near B2B , Shipra Path, Mansarovar, Phone:\nJaipur Email:\nVENDOR_ADDRESS: Fly\n'N'\nFit\nCentre\n& Fitness JPR\nPhysiotherapy Mansarovar,\n4/164, S SFS, Near\nVENDOR_NAME: FIT 'N' FLY [ Physiotherapy & Fitness]\nVENDOR_NAME: Fit N.Fly\nPhone:: 8875777711\n\n=== ADDITIONAL DOCUMENT DETAILS ===\n\nAmount Paid INR: 500.00 Amount Received:: 500.00 INR Patient Id:: F-694 Date:: 15 Jul, 2025 Date: 15 Jul, 2025 Invoice Number:: I-1414 Receipt Number: R-1419 Total Cost:: 500.00 INR Grand Total:: 500.00 INR Balance Amount :: 0.00 INR Balance Amount :: 0.00 INR Email:: fitnflyphysio@gmail.com By:: Dr. Digvijay Rathore Date: 15 Jul, 2025 Mode Of Payment: Card Generated On: 18 Jul 2025 Page: of 1 OPPO: A78 5G #: 1. Treatments & Products: Physiotherapy Treatment\nDate 15 Jul, 2025 Unit Cost INR: 500.00 Qty: 1 Total Cost INR: 500.00  | \n\nRaw Text Content:\nFit\nN.Fly\nFIT 'N' FLY [ Physiotherapy & Fitness]\nPhyalothorapy & Fitness Centre\n4/164, SFS, Near B2B , Shipra Path, Mansarovar,\nPhone: 8875777711\nJaipur\nEmail: fitnflyphysio@gmail.com\nSuresh Saini\nMale, 30 Years\nPatient Id: F-694\nBy: Dr. Digvijay Rathore\nInvoices\nDate: 15 Jul, 2025\nInvoice Number: I-1414\n#\nTreatments & Products\nUnit Cost INR\nQty\nTotal Cost INR\n1.\nPhysiotherapy Treatment\n500.00\n1\n500.00\nDate\n15 Jul, 2025\nTotal Cost: 500.00 INR\nPayment Details\nGrand Total: 500.00 INR\nDate\nReceipt Number Mode Of Payment Amount Paid INR\nAmount Received: 500.00 INR\n15 Jul, 2025\nR-1419\nCard\n500.00\nBalance Amount : 0.00 INR\nThank You - We Wishing you good health & happiness!!!!\nFit\n'N'\nFly\n4/164, S Physiotherapy SFS, Near & Fitness Mansarovar, Centre JPR\nGenerated On 18 Jul 2025\nPage of 1\nPowered by Practo\nOPPO A78 5G",
  "gold": {
    "invoice_number": "I-1414",
    "patient_name": "Suresh Saini",
    "services": [
      {
        "service": "Physiotherapy Treatment",
        "amount": 500,
        "quantity": 1,
        "department": "consultation",
        "unit": null,
        "mrp": 0,
        "cgst": 0,
        "cgst_type": null,
        "sgst": 0,
        "sgst_type": null,
        "gst": 0,
        "gst_type": null
      }
    ],
    "total_amount": 500,
    "doctor_name": "Dr. Digvijay Rathore",
    "facility": "FIT 'N' FLY [ Physiotherapy & Fitness] 4/164, SFS, Near B2B, Shipra Path, Mansarovar, Jaipur Phone: 8875777711 Email: fitnflyphysio@gmail.com",
    "invoice_date": "15 Jul, 2025",
    "payment_mode": "Card",
    "patient_age": "30 Years",
    "patient_gender": "Male",
    "patient_contact": null,
    "cgst": 0,
    "cgst_type": null,
    "sgst": 0,
    "sgst_type": null,
    "gst": 0,
    "gst_type": null,
    "discount": 0,
    "mrp": 0,
    "round_off": 0
  }
}