{
  "file_id": "image_picker_02407DD2_54C0_476B_BBE1_DC6E94B73AEC_9119_000003A617CA5B69",
  "raw_text": "=== CUSTOMER INFORMATION ===\nName :: Mr.RATHEESH\nName :: Mr.RATHEESH\nMobile No :: 6666666666\n\n=== SUPPLIER INFORMATION ===\nADDRESS: Bangalore RRL\n-\n#46,27th Cross, 3rd Main\nRoad, Jayanagar, 7th Block,\nBangalore,08049364444,\nSTREET: #46,27th Cross, 3rd Main\nRoad, Jayanagar, 7th Block,\nCITY: Bangalore\nZIP_CODE: Bangalore,08049364444,\nADDRESS_BLOCK: Bangalore RRL\n-\n#46,27th Cross, 3rd Main\nRoad, Jayanagar, 7th Block,\nBangalore,08049364444,\nNAME: Tenet Diagnostics Pvt Ltd\nNAME: tenet\nDIAGNOSTICS\nGST:: 29AAICT7175N1ZE\nVENDOR_ADDRESS: Bangalore RRL\n-\n#46,27th Cross, 3rd Main\nRoad, Jayanagar, 7th Block,\nBangalore,08049364444,\nVENDOR_NAME: Tenet Diagnostics Pvt Ltd\nVENDOR_NAME: tenet\nDIAGNOSTICS\nVENDOR_PHONE: 98863 48863\n\n=== ADDITIONAL DOCUMENT DETAILS ===\n\nReg.Dt :: 28-Feb-2025 Req No :: BIL5361687 INVOICE_RECEIPT_ID: UMR2566604 GST:: 29AAICT7175N1ZE TID :: UMR2566604 Age/Gender :: 48 Years/Male Ref.By :: DR HARISH K V Email :: - Reference :: Hansaa Health Care & Research\nCentre Pvt. Ltd. Printed By/Date Time :: nishchaldn/28-Feb-2025 10: 27 AM Created By/Date time :: nishchaldn/28-Feb-2025 10: 26 AM S.No: 1 Service Cd: TNT0408 Service Name: Hemogram Rate: 450.00 Net Amount: 450.00  | S.No: 2 Service Cd: TNT0511 Service Name: Lipid Profile Rate: 600.00 Net Amount: 600.00  | S.No: 3 Service Cd: TNT0514 Service Name: Liver Function Test (LFT) Rate: 840.00 Net Amount: 840.00  | S.No: 4 Service Cd: TNT60669 Service Name: RFT Profile-1 Rate: 1,200.00 Net Amount: 1,200.00  | S.No: 5 Service Cd: TNT0370 Service Name: Glycosylated Hemoglobin (HbA1C) Rate: 700.00 Net Amount: 700.00  | S.No: 6 Service Cd: TNT0366 Service Name: Glucose Random (RBS) Rate: 80.00 Net Amount: 80.00  | S.No: 7 Service Cd: TNT0600 Service Name: Prostate Specific Antigen (PSA) Free Rate: 1,210.00 Net Amount: 1,210.00  | S.No: 8 Service Cd: TNT0601 Service Name: Prostate Specific Antigen (PSA) Total Rate: 950.00 Net Amount: 950.00  | S.No: 9 Service Cd: TNT1053 Service Name: 2D Echo/Doppler Study Rate: 2,000.00 Net Amount: 2,000.00  | \n\nRaw Text Content:\nBangalore - RRL\nTID\n: UMR2566604\nReq No\n: BIL5361687\ntenet\n#46,27th Cross, 3rd Main\nName\n: Mr.RATHEESH\nMobile No\n: 6666666666\nDIAGNOSTICS\nRoad, Jayanagar, 7th Block,\nAge/Gender\n: 48 Years/Male\nReg.Dt\n: 28-Feb-2025 10:26.36 AM\nIt's Good to Know\nBangalore,08049364444,\nRef.By\n: DR HARISH K V\nEmail\n:\n-\n98863 48863\nGST:29AAICT7175N1ZE\nReference\n:\nHansaa Health Care & Research\nCentre Pvt. Ltd.\nTenet Diagnostics Pvt Ltd\nBill Cum Receipt\nS.No\nService Cd\nService Name\nRate\nDiscount\nNet Amount\nCan.amt\n1\nTNT0408\nHemogram\n450.00\n450.00\n2\nTNT0511\nLipid Profile\n600.00\n600.00\n3\nTNT0514\nLiver Function Test (LFT)\n840.00\n840.00\n4\nTNT60669\nRFT Profile-1\n1,200.00\n1,200.00\nCreatinine, Serum,Blood Urea Nitrogen\n(BUN), Electrolytes, Serum, Complete Urine\nExamination (CUE), Uric Acid, Serum\n5\nTNT0370\nGlycosylated Hemoglobin (HbA1C)\n700.00\n700.00\n6\nTNT0366\nGlucose Random (RBS)\n80.00\n80.00\n7\nTNT0600\nProstate Specific Antigen (PSA) Free\n1,210.00\n1,210.00\n8\nTNT0601\nProstate Specific Antigen (PSA) Total\n950.00\n950.00\n9\nTNT1053\n2D Echo/Doppler Study\n2,000.00\n2,000.00\ncloss\nThis is an Electronically Generated Receipt & Does Not Require Signature *\nBIL5361687\nUMR2566604\nPrinted By/Date Time : nishchaldn/28-Feb-2025 10:27 AM\nCreated By/Date time : nishchaldn/28-Feb-2025 10:26 AM\nBy availing the above Service(s) and accepting this Bill cum Receipt, you indicate that you have read the Terms and Conditions, Privacy Policy, Refund and\nCancellation Policy available on www.tenetdiagnostics.in (as modified from time to time) and agree to be bound by the same.\n2nd\nBP\\",
  "gold": {
    "invoice_number": "BIL5361687",
    "patient_name": "Mr.RATHEESH",
    "services": [
      {
        "service": "Hemogram",
        "amount": 450,
        "quantity": 1,
        "department": "laboratory",
        "unit": null,
        "mrp": 450,
        "cgst": 0,
        "cgst_type": null,
        "sgst": 0,
        "sgst_type": null,
        "gst": 0,
        "gst_type": null
      },
      {
        "service": "Lipid Profile",
        "amount": 600,
        "quantity": 1,
        "department": "laboratory",
        "unit": null,
        "mrp": 600,
        "cgst": 0,
        "cgst_type": null,
        "sgst": 0,
        "sgst_type": null,
        "gst": 0,
        "gst_type": null
      },
      {
        "service": "Liver Function Test (LFT)",
        "amount": 840,
        "quantity": 1,
        "department": "laboratory",
        "unit": null,
        "mrp": 840,
        "cgst": 0,
        "cgst_type": null,
        "sgst": 0,
        "sgst_type": null,
        "gst": 0,
        "gst_type": null
      },
      {
        "service": "RFT Profile-1(Creatinine,Serum,Blood,Urea,Nitrogen(BUN),Electrolytes,Serum,Complete Urine Examination(CUE),Uric Acid,Serum)",
        "amount": 1200,
        "quantity": 1,
        "department": "laboratory",
        "unit": null,
        "mrp": 1200,
        "cgst": 0,
        "cgst_type": null,
        "sgst": 0,
        "sgst_type": null,
        "gst": 0,
        "gst_type": null
      },
      {
        "service": "Glycosylated Hemoglobin (HbA1C)",
        "amount": 700,
        "quantity": 1,
        "department": "laboratory",
        "unit": null,
        "mrp": 700,
        "cgst": 0,
        "cgst_type": null,
        "sgst": 0,
        "sgst_type": null,
        "gst": 0,
        "gst_type": null
      },
      {
        "service": "Glucose Random (RBS)",
        "amount": 80,
        "quantity": 1,
        "department": "laboratory",
        "unit": null,
        "mrp": 80,
        "cgst": 0,
        "cgst_type": null,
        "sgst": 0,
        "sgst_type": null,
        "gst": 0,
        "gst_type": null
      },
      {
        "service": "Prostate Specific Antigen (PSA) Free",
        "amount": 1210,
        "quantity": 1,
        "department": "laboratory",
        "unit": null,
        "mrp": 1210,
        "cgst": 0,
        "cgst_type": null,
        "sgst": 0,
        "sgst_type": null,
        "gst": 0,
        "gst_type": null
      },
      {
        "service": "Prostate Specific Antigen (PSA) Total",
        "amount": 950,
        "quantity": 1,
        "department": "laboratory",
        "unit": null,
        "mrp": 950,
        "cgst": 0,
        "cgst_type": null,
        "sgst": 0,
        "sgst_type": null,
        "gst": 0,
        "gst_type": null
      },
      {
        "service": "2D Echo/Doppler Study",
        "amount": 2000,
        "quantity": 1,
        "department": "radiology",
        "unit": null,
        "mrp": 2000,
        "cgst": 0,
        "cgst_type": null,
        "sgst": 0,
        "sgst_type": null,
        "gst": 0,
        "gst_type": null
      }
    ],
    "total_amount": 8030,
    "doctor_name": "DR HARISH K V",
    "facility": "Tenet Diagnostics Pvt Ltd, #46,27th Cross, 3rd Main Road, Jayanagar, 7th Block, Bangalore, 08049364444, 98863 48863",
    "invoice_date": "28-Feb-2025 10:26.36 AM",
    "payment_mode": null,
    "patient_age": "48 Years",
    "patient_gender": "Male",
    "patient_contact": "6666666666",
    "cgst": 0,
    "cgst_type": null,
    "sgst": 0,
    "sgst_type": null,
    "gst": 0,
    "gst_type": null,
    "discount": 0,
    "mrp": 8030,
    "round_off": 0
  }
}