{
  "file_id": "image_picker_BA045B38_EAC3_4CE4_8A31_D41E09F74C93_2012_0000268C1B190919",
  "raw_text": "=== CUSTOMER INFORMATION ===\nAddress :: .,Whitefield,Karnataka,0\nCITY: .,Whitefield,Karnataka,0\nADDRESS_BLOCK: .,Whitefield,Karnataka,0\nPatient Name :: Mr. ANIRUDH\nAddress :: .,Whitefield,Karnataka,0\nPatient Name :: Mr. ANIRUDH\nPhone No :: 9995918735\n\n=== SUPPLIER INFORMATION ===\nADDRESS: Telerad RxDx Healthcare Private Limited\nRxDx Whitefield, Plot No. 7G, Opp., Graphite India,\nKundalahalli Main Road, Whitefield, Bengaluru - 560048\nSTREET: Kundalahalli Main Road,\nSTREET: Plot No. 7G, Opp., Graphite\nCITY: Bengaluru\nZIP_CODE: 560048\nCOUNTRY: India,\nNAME: Telerad RxDx Healthcare Private Limited\nADDRESS_BLOCK: RxDx Whitefield, Plot No. 7G, Opp., Graphite India,\nKundalahalli Main Road, Whitefield, Bengaluru - 560048\nNAME: RxDx\nGST No :: 29AACCT6769N1ZE\nVENDOR_ADDRESS: Telerad RxDx Healthcare Private Limited\nRxDx Whitefield, Plot No. 7G, Opp., Graphite India,\nKundalahalli Main Road, Whitefield, Bengaluru - 560048\nVENDOR_NAME: Telerad RxDx Healthcare Private Limited\nVENDOR_NAME: RxDx\nt: 901 996 1402\nVENDOR_PHONE: 901 409 1111\n\n=== ADDITIONAL DOCUMENT DETAILS ===\n\nDate :: 21-Oct-2024 Bill/Rcpt :: WFPG156138/WFPG155329 (Trans No. :: : LBO190.253039755, GST No :: 29AACCT6769N1ZE Taxable :: 1,273.13 SGST :: 76.38 CGST: 76.38 Total\n:: 1,425.89 Patient Due\n:: 0.000 Patient Due\n:: 0.000 TOTAL: Type: UPI Pinelab.)\nTHOUSAND FOUR HUNDRED TWENTY-SIX ONLY UHID :: RXWF.470434 DL. No :: KA-B61-173771,KA-B61-17377\n2 Age/Sex :: 33 Year(s) / Male Doctor :: Dr.Kapendra Mouli Cess :: 0.00 Run Date :: 21-Oct-2024 1: 53 pm Page: 1 of 2 Sr No: 1 Particulars\nMFR / HSN: DEFCORT 6MG TAB\nMACLE/30043200 Qty: 10 Expiry /\nBatch: 13240273A MRP: 15.00 Disc\n%: 0.00 Rate: 15.00 GST %: 12.00 Amount: 150.01  | Sr No: 2 Particulars\nMFR / HSN: NUBALIN-PLUS TAB\nMEDFO/30049082 Qty: 6 Expiry /\nBatch: GT231902 MRP: 19.99 Disc\n%: 0.00 Rate: 19.99 GST %: 12.00 Amount: 119.94  | Sr No: 3 Particulars\nMFR / HSN: CADEL/30049039 Qty: 20 Expiry /\nBatch: Aug-26/\nPLSR9241 MRP: 8.80 Disc\n%: 0,00 Rate: 8.80 GST %: 12.00 Amount: 175.98 Particulars\nMFR / HSN: PANTODELL DSR CAP\n10S\nCADEL/30049039  | Sr No: 4 Particulars\nMFR / HSN: PHARM/30049099 Qty: 20 Expiry /\nBatch: Jul-27/\nTETR24008 MRP: 37.00 Disc\n%: 0.00 Rate: 37.00 GST %: 12.00 Amount: 740.00 Particulars\nMFR / HSN: TRIACTIN 8MG TAB\n10S  | Sr No: 5 Particulars\nMFR / HSN: NANOFAST GEL\nPHARM/30049099 Expiry /\nBatch: NN24029 MRP: 160.00 Disc\n%: 0.00 Rate: 160.00 GST %: 12.00 Amount: 160.00  | Sr No: 6 Particulars\nMFR / HSN: NUBALIN-PLUS TAB\nMEDFO/30049082 Expiry /\nBatch: Oct-25/\nGT231902 MRP: 19.99 Disc\n%: 0,00 Rate: 19.99 GST %: 12.00 Amount: 79.96  | \n\nRaw Text Content:\nTelerad RxDx Healthcare Private Limited\nRxDx Whitefield, Plot No. 7G, Opp., Graphite India,\nKundalahalli Main Road, Whitefield, Bengaluru - 560048\nRxDx\nMC-6085\nC\n901 409 1111\nt\n901 996 1402\nrxdx.in I lab@rxdx.in\nBe At Your Best. Everyday.\nPharmacy - Whitefield GF (Tax Invoice)\nUHID\n: RXWF.470434\nDate\n: 21-Oct-2024 1:53 pm\nPatient Name\n:\nMr. ANIRUDH\nDL. No\n: KA-B61-173771,KA-B61-17377\n2\nAge/Sex\n: 33 Year(s) / Male\nBill/Rcpt\n: WFPG156138/WFPG155329\nDoctor\n: Dr.Kapendra Mouli\nGST No\n: 29AACCT6769N1ZE\nAddress\n:\n.,Whitefield,Karnataka,0\nPhone No : 9995918735\nParticulars\nSr No\nQty\nExpiry /\nDisc\nMRP\nRate\nGST %\nAmount\nMFR / HSN\nBatch\n%\n1\nDEFCORT 6MG TAB\n10\nMay-27/\n15.00\n0.00\n15.00\n12.00\n150.01\nMACLE/30043200\n13240273A\n2\nNUBALIN-PLUS TAB\n6\nOct-25/\n19.99\n0.00\n19.99\n12.00\n119.94\nMEDFO/30049082\nGT231902\n3\nPANTODELL DSR CAP\n20\nAug-26/\n8.80\n0,00\n8.80\n12.00\n175.98\n10S\nPLSR9241\nCADEL/30049039\n4\nTRIACTIN 8MG TAB\n20\nJul-27/\n37.00\n0.00\n37.00\n12.00\n740.00\n10S\nTETR24008\nPHARM/30049099\n5\nNANOFAST GEL\nJul-26/\n160.00\n0.00\n160.00\n12.00\n160.00\nPHARM/30049099\nNN24029\n6\nNUBALIN-PLUS TAB\nOct-25/\n19.99\n0,00\n19.99\n12.00\n79.96\nMEDFO/30049082\nGT231902\nTaxable : 1,273.13\nSGST : 76.38\nCGST 76.38\nCess : 0.00\nTotal : 1,425.89\nAmt\n:\nPatient Due\n:\n0.000\nOther Payment for Rs. 1426 (Trans No. :LBO190.253039755, Payment\nType:UPI Pinelab.)\nRUPEES ONE THOUSAND FOUR HUNDRED TWENTY-SIX ONLY\nSignature\nVerified by Pharmagist\nKeerthana\nName :\nX\nRun Date : 21-Oct-2024 1:53 pm\nPage 1 of 2",
  "gold": {
    "invoice_number": "WFPG156138/WFPG155329",
    "patient_name": "Mr. ANIRUDH",
    "services": [
      {
        "service": "DEFCORT 6MG TAB",
        "amount": 150.01,
        "quantity": 10,
        "department": "pharmacy",
        "unit": "tablets",
        "mrp": 15.0,
        "cgst": 0,
        "cgst_type": null,
        "sgst": 0,
        "sgst_type": null,
        "gst": 12.0,
        "gst_type": "PERCENT"
      },
      {
        "service": "NUBALIN-PLUS TAB",
        "amount": 119.94,
        "quantity": 6,
        "department": "pharmacy",
        "unit": "tablets",
        "mrp": 19.99,
        "cgst": 0,
        "cgst_type": null,
        "sgst": 0,
        "sgst_type": null,
        "gst": 12.0,
        "gst_type": "PERCENT"
      },
      {
        "service": "PANTODELL DSR CAP 10S",
        "amount": 175.98,
        "quantity": 20,
        "department": "pharmacy",
        "unit": "capsules",
        "mrp": 8.8,
        "cgst": 0,
        "cgst_type": null,
        "sgst": 0,
        "sgst_type": null,
        "gst": 12.0,
        "gst_type": "PERCENT"
      },
      {
        "service": "TRIACTIN 8MG TAB 10S",
        "amount": 740.0,
        "quantity": 20,
        "department": "pharmacy",
        "unit": "tablets",
        "mrp": 37.0,
        "cgst": 0,
        "cgst_type": null,
        "sgst": 0,
        "sgst_type": null,
        "gst": 12.0,
        "gst_type": "PERCENT"
      },
      {
        "service": "NANOFAST GEL",
        "amount": 160.0,
        "quantity": 1,
        "department": "pharmacy",
        "unit": "gel",
        "mrp": 160.0,
        "cgst": 0,
        "cgst_type": null,
        "sgst": 0,
        "sgst_type": null,
        "gst": 12.0,
        "gst_type": "PERCENT"
      },
      {
        "service": "NUBALIN-PLUS TAB",
        "amount": 79.96,
        "quantity": 4,
        "department": "pharmacy",
        "unit": "tablets",
        "mrp": 19.99,
        "cgst": 0,
        "cgst_type": null,
        "sgst": 0,
        "sgst_type": null,
        "gst": 12.0,
        "gst_type": "PERCENT"
      }
    ],
    "total_amount": 1425.89,
    "doctor_name": "Dr.Kapendra Mouli",
    "facility": "Telerad RxDx Healthcare Private Limited RxDx Whitefield, Plot No. 7G, Opp., Graphite India, Kundalahalli Main Road, Whitefield, Bengaluru - 560048",
    "invoice_date": "21-Oct-2024 1:53 pm",
    "payment_mode": "UPI Pinelab",
    "patient_age": "33 Year(s)",
    "patient_gender": "Male",
    "patient_contact": "9995918735",
    "cgst": 76.38,
    "cgst_type": "AMOUNT",
    "sgst": 76.38,
    "sgst_type": "AMOUNT",
    "gst": 0,
    "gst_type": null,
    "discount": 0,
    "mrp": 0,
    "round_off": 0
  }
}