{
  "file_id": "1000181401",
  "raw_text": "=== CUSTOMER INFORMATION ===\nNAME: Ms.KULSUMA\nBEGUM BARBHULYA\nRECEIVER_NAME: Ms.KULSUMA\nBEGUM BARBHULYA\n\n=== SUPPLIER INFORMATION ===\nADDRESS: ST. JOHN'S MEDICAL COLLEGE HOSPITAL\n(A unit of CBCI Society for Medical Education)\nSARJAPURA ROAD, BENGALURU 560034\n-\nSTREET: SARJAPURA ROAD,\nCITY: BENGALURU\nZIP_CODE: 560034\nNAME: ST. JOHN'S MEDICAL COLLEGE HOSPITAL\nADDRESS_BLOCK: SARJAPURA ROAD, BENGALURU 560034\n-\nNAME: NASH\nGSTIN: 29AAATC0773E1ZX\nVENDOR_ADDRESS: ST. JOHN'S MEDICAL COLLEGE HOSPITAL\n(A unit of CBCI Society for Medical Education)\nSARJAPURA ROAD, BENGALURU 560034\n-\nVENDOR_NAME: ST. JOHN'S MEDICAL COLLEGE HOSPITAL\nVENDOR_NAME: NASH\nPhone:: +91 80 2206 5000\nBilling :: +91 80 2206 5080\n\n=== ADDITIONAL DOCUMENT DETAILS ===\n\nBILL NO: 90110061985 GSTIN: 29AAATC0773E1ZX GENERAL PROCEDURES: 1,320.00 NET TOTAL: 1,960.00 TOTAL: One Thousand Nine Hundred and Sixty Only Email:: sjmch.billing@stjohns.in UHID: 5301640 ENCOUNTER NO: 902507198040 BED NO.: 54 ADMISSION DATE & TIME: 19 Jul 2025 11:48:53 DISCHARGE DATE & TIME: 19 Jul 2025 13:19:11 PATIENT TYPE: SELF PAY IP No.: o CONCESSION: 0.00 PRINTED BY: MR. PRAVEEN KUMAR K.-N9009\n19 Jul202513:19:35 PREPARED BY: MR. PRAVEEN KUMAR K.\n19 Jul 2025 13:16:58 FINALIZED BY: MR. PRAVEEN KUMAR K.-N9\n19 Jul 2025 13:19:11 Note:: This detail bill to be read along with this summary bill provided. PARTICULARS: CONSULTATION AMOUNT(IN INR): 500.00  | DATE: 19 Jul 2025 PARTICULARS: Emergency Registration & Consultation UNIT PRICE: 500.00 UNITS: 1,0 AMOUNT(IN INR): 500.00  | DATE: 19 Jul 2025 PARTICULARS: Glucometer Random Blood Sugar UNIT PRICE: 80,00 UNITS: 1,0 AMOUNT(IN INR): 80.00  | DATE: 19 Jul 2025 PARTICULARS: Injection Service Charges in ER/OPD IV / IM\n- UNIT PRICE: 50.00 UNITS: 1.0 AMOUNT(IN INR): 50.00  | DATE: 19 Jul 2025 PARTICULARS: IV Cannulation in ER/Daycare UNIT PRICE: 100,00 UNITS: 1.0 AMOUNT(IN INR): 100.00  | DATE: 19 Jul 2025 PARTICULARS: ECG (Bedside) UNIT PRICE: 500.00 UNITS: 1.0 AMOUNT(IN INR): 500.00  | DATE: 19 Jul 2025 PARTICULARS: ABG Radiometer ER (Adult)\n- - UNIT PRICE: 590.00 UNITS: 1.0 AMOUNT(IN INR): 590.00  | DATE: 19 Jul 2025 PARTICULARS: Professional Charges in ER UNIT PRICE: 140.00 UNITS: 1.0 AMOUNT(IN INR): 140.00  | \n\nRaw Text Content:\nBECAUSE\nST. JOHN'S MEDICAL COLLEGE HOSPITAL\n(A unit of CBCI Society for Medical Education)\nNASH\nSARJAPURA ROAD, BENGALURU - 560034\nPhone: +91 80 2206 5000 / Billing : +91 80 2206 5080\nH-2020-0690\nEmail: sjmch.billing@stjohns.in\nEMERGENCY BILL - FULL BREAKUP\nMs.KULSUMA BEGUM BARBHULYA\nUHID\nENCOUNTER NO\n26 Y FEMALE\nNo111 Katlicherra Police Station, District,\nAssam-\n5301640\n902507198040\nBILL NO\n90110061985\nBED NO.\nADMISSION DATE & TIME\nDISCHARGE DATE & TIME\nPATIENT TYPE\n54\n19 Jul 2025 11:48:53\n19 Jul 2025 13:19:11\nSELF PAY\nEMERGENCY MEDICINE G Floor B BLOCK\nGSTIN\nIP No.\n29AAATC0773E1ZX\nE OF ME\no\nDATE\nPARTICULARS\nUNIT PRICE\nUNITS\nAMOUNT(IN INR)\nCONSULTATION\n500.00\n19 Jul 2025\nEmergency Registration & Consultation\n500.00\n1,0\n500.00\nGENERAL PROCEDURES\n1,320.00\n19 Jul 2025\nGlucometer Random Blood Sugar\n80,00\n1,0\n80.00\n19 Jul 2025\nInjection Service Charges in ER/OPD - IV / IM\n50.00\n1.0\n50.00\n19 Jul 2025\nIV Cannulation in ER/Daycare\n100,00\n1.0\n100.00\n19 Jul 2025\nECG (Bedside)\n500.00\n1.0\n500.00\n19 Jul 2025\nABG - Radiometer - ER (Adult)\n590.00\n1.0\n590.00\nPROFESSIONAL & TREATMENT CHARGES\n140.00\n19 Jul 2025\nProfessional Charges in ER\n140.00\n1.0\n140.00\nCONCESSION\n0.00\nNET TOTAL\n1,960.00\nOne Thousand Nine Hundred and Sixty Only\nPRINTED BY\nPREPARED BY\nFINALIZED BY\nMR. PRAVEEN KUMAR K.-N9009\nMR. PRAVEEN KUMAR K.\nare\nMR. PRAVEEN KUMAR K.-N9\n19 Jul202513:19:35\n19 Jul 2025 13:16:58\n19 Jul 2025 13:19:11\nNote: This detail bill to be read along with this summary bill provided.\nE & OE",
  "gold": {
    "invoice_number": "90110061985",
    "patient_name": "Ms.KULSUMA BEGUM BARBHULYA",
    "services": [
      {
        "service": "Emergency Registration & Consultation",
        "amount": 500,
        "quantity": null,
        "department": "consultation",
        "unit": 1,
        "mrp": 0,
        "cgst": 0,
        "cgst_type": null,
        "sgst": 0,
        "sgst_type": null,
        "gst": 0,
        "gst_type": null
      },
      {
        "service": "Glucometer Random Blood Sugar",
        "amount": 80,
        "quantity": null,
        "department": "laboratory",
        "unit": 1,
        "mrp": 0,
        "cgst": 0,
        "cgst_type": null,
        "sgst": 0,
        "sgst_type": null,
        "gst": 0,
        "gst_type": null
      },
      {
        "service": "Injection Service Charges in ER/OPD - IV / IM",
        "amount": 50,
        "quantity": null,
        "department": "emergency",
        "unit": 1,
        "mrp": 0,
        "cgst": 0,
        "cgst_type": null,
        "sgst": 0,
        "sgst_type": null,
        "gst": 0,
        "gst_type": null
      },
      {
        "service": "IV Cannulation in ER/Daycare",
        "amount": 100,
        "quantity": null,
        "department": "emergency",
        "unit": 1,
        "mrp": 0,
        "cgst": 0,
        "cgst_type": null,
        "sgst": 0,
        "sgst_type": null,
        "gst": 0,
        "gst_type": null
      },
      {
        "service": "ECG (Bedside)",
        "amount": 500,
        "quantity": null,
        "department": "radiology",
        "unit": 1,
        "mrp": 0,
        "cgst": 0,
        "cgst_type": null,
        "sgst": 0,
        "sgst_type": null,
        "gst": 0,
        "gst_type": null
      },
      {
        "service": "ABG - Radiometer - ER (Adult)",
        "amount": 590,
        "quantity": null,
        "department": "laboratory",
        "unit": 1,
        "mrp": 0,
        "cgst": 0,
        "cgst_type": null,
        "sgst": 0,
        "sgst_type": null,
        "gst": 0,
        "gst_type": null
      },
      {
        "service": "Professional Charges in ER",
        "amount": 140,
        "quantity": null,
        "department": "emergency",
        "unit": 1,
        "mrp": 0,
        "cgst": 0,
        "cgst_type": null,
        "sgst": 0,
        "sgst_type": null,
        "gst": 0,
        "gst_type": null
      }
    ],
    "total_amount": 1960,
    "doctor_name": null,
    "facility": "ST. JOHN'S MEDICAL COLLEGE HOSPITAL (A unit of CBCI Society for Medical Education) SARJAPURA ROAD, BENGALURU - 560034 Phone: +91 80 2206 5000 / Billing : +91 80 2206 5080 Email: sjmch.billing@stjohns.in",
    "invoice_date": "19 Jul 2025 13:19:11",
    "payment_mode": null,
    "patient_age": "26 Y",
    "patient_gender": "Female",
    "patient_contact": null,
    "cgst": 0,
    "cgst_type": null,
    "sgst": 0,
    "sgst_type": null,
    "gst": 0,
    "gst_type": null,
    "discount": 0,
    "mrp": 0,
    "round_off": 0
  }
}