{
  "file_id": "1000083141",
  "raw_text": "=== CUSTOMER INFORMATION ===\nPatient Name :: MR. CHANDRAMOHAN SHETTY\nPatient Name :: MR. CHANDRAMOHAN SHETTY\n\n=== SUPPLIER INFORMATION ===\nADDRESS: Plot no 16. Panchavati Naka, Ambadi Road Vasai (W), Dist. Plaghar - 401202.\nSTREET: Plot no 16. Panchavati Naka, Ambadi Road Vasai (W),\nCITY: Plaghar\nZIP_CODE: 401202.\nADDRESS_BLOCK: Plot no 16. Panchavati Naka, Ambadi Road Vasai (W), Dist. Plaghar - 401202.\nNAME: BAXAY PRIME\nMULTISPECIALITY\nHOSPITAL AND ICU\nNAME: BAXAY\nE A T\nVENDOR_ADDRESS: Plot no 16. Panchavati Naka, Ambadi Road Vasai (W), Dist. Plaghar - 401202.\nVENDOR_NAME: BAXAY PRIME\nMULTISPECIALITY\nHOSPITAL AND ICU\nVENDOR_NAME: BAXAY\nE A T\nM.:: 9044431777\nVENDOR_PHONE: 9044432777\nVENDOR_URL: www.shreecare.com\n\n=== ADDITIONAL DOCUMENT DETAILS ===\n\nAmount Paid :: Rs.2000 Bill Date :: 26/12/2024 Bill No :: 5555 Total Bill :: Rs.2000 Net Total Bill :: Rs.2000 TOTAL: (Two Thousand Only) TOTAL: (Two Thousand Only) Registration No. :: 4441 Age e/Gender :: 60 Years / Male Registration Date :: 26/12/2024 Consultant Doctor :: DR RAVISH RAVAL (CARDIOLOGIST) Referred by :: SELF Lab No :: 0 Balance * :: Rs.0 Print Date and Time: 26/12/2024 03:47:10 Bill Generated By :: VINAY Page: 1/1 SNo.: 1 Particulars: 2 D Echo Qty: 1 Rate: 2000 Total: 2000  | \n\nRaw Text Content:\nBAXAY\nBAXAY PRIME\nMULTISPECIALITY\nE\nA\nT\nHOSPITAL AND ICU\nPlot no 16. Panchavati Naka, Ambadi Road Vasai (W), Dist. Plaghar - 401202.\nM.: 9044431777 9044432777\nOPD Bill CUM RECEIPT\nPatient Name\n: MR. CHANDRAMOHAN SHETTY\nRegistration No. : 4441\nAge e/Gender\n: 60 Years / Male\nRegistration Date : 26/12/2024\nConsultant Doctor\n:\nDR RAVISH RAVAL (CARDIOLOGIST)\nBill No\n: 5555\nReferred by\n: SELF\nBill Date\n: 26/12/2024 3:45 PM\nLab No\n: 0\nSNo.\nParticulars\nQty\nRate\nTotal\n1\n2 D Echo\n1\n2000\n2000\n(Two Thousand Only)\nTotal Bill\n: Rs.2000\nNet Total Bill\n: Rs.2000\n(Two Thousand Only)\nAmount Paid\n: Rs.2000\nBalance *\n: Rs.0\nThis bill print using Shreecare. www.shreecare.com\nPrint Date and Time 26/12/2024\nSECURITY 03:47:10 Signature and ISIO DEPARTMENT People\n20>,\nBill Generated By :VINAY\nPage 1/1",
  "gold": {
    "invoice_number": "5555",
    "patient_name": "MR. CHANDRAMOHAN SHETTY",
    "services": [
      {
        "service": "2 D Echo",
        "amount": 2000,
        "quantity": 1,
        "department": "radiology",
        "unit": null,
        "mrp": 0,
        "cgst": 0,
        "cgst_type": null,
        "sgst": 0,
        "sgst_type": null,
        "gst": 0,
        "gst_type": null
      }
    ],
    "total_amount": 2000,
    "doctor_name": "DR RAVISH RAVAL (CARDIOLOGIST)",
    "facility": "BAXAY PRIME MULTISPECIALITY HOSPITAL AND ICU Plot no 16. Panchavati Naka, Ambadi Road Vasai (W), Dist. Plaghar - 401202. M.: 9044431777 9044432777",
    "invoice_date": "26/12/2024 3:45 PM",
    "payment_mode": null,
    "patient_age": "60 Years",
    "patient_gender": "Male",
    "patient_contact": null,
    "cgst": 0,
    "cgst_type": null,
    "sgst": 0,
    "sgst_type": null,
    "gst": 0,
    "gst_type": null,
    "discount": 0,
    "mrp": 0,
    "round_off": 0
  }
}