{
  "file_id": "acf268a3_0b48_4e4c_9d4d_f48f1a23bf0c2795271242579248702",
  "raw_text": "=== CUSTOMER INFORMATION ===\nPATIENT\nNAME\n:: BHUMI\nPATIENT\nNAME\n:: BHUMI\n\n=== SUPPLIER INFORMATION ===\nADDRESS: SANTOSH MEDICOSE\nA-7, SHOP NO.1, EAST UTTAM NAGAR, HANUMAN MKT NEW DELHI-59.\nSTREET: A-7, SHOP NO.1, EAST UTTAM NAGAR, HANUMAN MKT\nCITY: NEW\nNAME: SANTOSH MEDICOSE\nADDRESS_BLOCK: A-7, SHOP NO.1, EAST UTTAM NAGAR, HANUMAN MKT NEW DELHI-59.\nNAME: SANTOSH MEDICOSE\nVENDOR_ADDRESS: SANTOSH MEDICOSE\nA-7, SHOP NO.1, EAST UTTAM NAGAR, HANUMAN MKT NEW DELHI-59.\nVENDOR_NAME: SANTOSH MEDICOSE\nVENDOR_NAME: SANTOSH MEDICOSE\nPh.: 9818890860\n\n=== ADDITIONAL DOCUMENT DETAILS ===\n\nDATE: 27/05/2024 CASH MEMO NO. :: 3351 TOTAL AMOUNT :: 824.08 CGST:: 40.52 SGST:: 40.52 Net Amt.(R/0) :: 824.00 TOTAL: Rupees Eight Hundred Twenty Four Only D.L.No.:: DL-UTN-110949,110950 :\nPRESCRIBED\nBY\n:: ANIL ARORA Inclusive GST Amount in this Invoice :: 81.04) PARTICULARS\nIBUGESIC SYP.: IBUGESIC SYP. BATCH No.: SE31047 RATE: 24.64 Amount: 24.64  | PARTICULARS\nIBUGESIC SYP.: REFLORA - R SACHET PACK: 100ML\n1GM QTY: 1\n10 BATCH No.: SE2309A EXP: 10/25\n05/25 GST%: 12.00\n12.00 RATE: 129.00 Amount: 129.00  | PARTICULARS\nIBUGESIC SYP.: JUNIOR LANZOL 15 TAB PACK: 1GM\n15 TAB QTY: 10 BATCH No.: 12SRE091 EXP: 05/25\n10/25 GST%: 12.00\n12.00 RATE: 39.00 Amount: 390.00  | PARTICULARS\nIBUGESIC SYP.: CYCLOPAM SYP PACK: 30ML QTY: 1 BATCH No.: 24430117 EXP: 10/25\n09/26 GST%: 12.00\n12.00 RATE: 99.00 Amount: 99.00  | PARTICULARS\nIBUGESIC SYP.: -\nELECTRAL APPLE FLAVOR 200ML QTY: 2 BATCH No.: 353H003 EXP: 01/25 GST%: 5.00 RATE: 29.40 Amount: 58.80  | PARTICULARS\nIBUGESIC SYP.: ELECTRAL - APPLE FLAVOR 200ML QTY: 2 BATCH No.: 353K037 EXP: 04/25 GST%: 5.00 RATE: 31.50 Amount: 63.00  | \n\nRaw Text Content:\n07ARHPG9259R1ZV\nD.L.No.: DL-UTN-110949,110950\nRETAIL INVOICE/CASH MEMO\nSANTOSH MEDICOSE\nA-7, SHOP NO.1, EAST UTTAM NAGAR, HANUMAN MKT NEW DELHI-59.\nPh. 9818890860\nCASH MEMO NO. : 3351\nDATE 27/05/2024\nPATIENT NAME :\nBHUMI\nPATIENT ADD\n:\nPRESCRIBED BY\n: ANIL ARORA\nPARTICULARS\nPACK\nQTY\nBATCH No.\nEXP\nGST%\nRATE\nAmount\nIBUGESIC SYP.\n100ML\nCHERICOF SYP 100ML\n1\nSE31047\n11/26\n12.00\n24.64\n24.64\n100ML\nREFLORA - R SACHET\n1\nSE2309A\n10/25\n12.00\n129.00\n129.00\n1GM\n10\n12SRE091\n05/25\n12.00\n39.00\n390.00\nJUNIOR LANZOL 15 TAB\n15 TAB\n5\nBA33310\n10/25\n12.00\n178.91\n59.64\nCYCLOPAM SYP\n30ML\n1\n24430117\n09/26\n12.00\n99.00\n99.00\nELECTRAL - APPLE FLAVOR\n200ML\n2\n353H003\n01/25\n5.00\n29.40\n58.80\nELECTRAL - APPLE FLAVOR\n200ML\n2\n353K037\n04/25\n5.00\n31.50\n63.00\nINCL. GST DETAILS :\nCGST:\n40.52\nSGST:\n40.52\n( Inclusive GST Amount in this Invoice : 81.04)\nTOTAL AMOUNT :\n824.08\nGST DETAIL : 0,00 X 5 9 % = 0.00\n:\nNet Amt.(R/0)\n:\n824.00\nRupees Eight Hundred Twenty Four Only\nE.& O.E.\nAll disputes are subject to Delhi Jurisdiction.\nFor SANTOSH MEDICOSE\nno return cutting medicines\nshow your medicine doctor before taken\n(Computer Generated Invoice)",
  "gold": {
    "invoice_number": "3351",
    "patient_name": "BHUMI",
    "services": [
      {
        "service": "IBUGESIC SYP.",
        "amount": 24.64,
        "quantity": 1,
        "department": "pharmacy",
        "unit": "100ML",
        "mrp": 24.64,
        "cgst": 0,
        "cgst_type": null,
        "sgst": 0,
        "sgst_type": null,
        "gst": 12,
        "gst_type": "PERCENT"
      },
      {
        "service": "CHERICOF SYP 100ML",
        "amount": 129,
        "quantity": 1,
        "department": "pharmacy",
        "unit": "100ML",
        "mrp": 129,
        "cgst": 0,
        "cgst_type": null,
        "sgst": 0,
        "sgst_type": null,
        "gst": 12,
        "gst_type": null
      },
      {
        "service": "REFLORA - R SACHET",
        "amount": 390,
        "quantity": 10,
        "department": "pharmacy",
        "unit": "1GM",
        "mrp": 39,
        "cgst": 0,
        "cgst_type": null,
        "sgst": 0,
        "sgst_type": null,
        "gst": 12,
        "gst_type": "PERCENT"
      },
      {
        "service": "JUNIOR LANZOL 15 TAB",
        "amount": 59.64,
        "quantity": 5,
        "department": "pharmacy",
        "unit": "15 TAB",
        "mrp": 178.91,
        "cgst": 0,
        "cgst_type": null,
        "sgst": 0,
        "sgst_type": null,
        "gst": 12,
        "gst_type": "PERCENT"
      },
      {
        "service": "CYCLOPAM SYP",
        "amount": 99,
        "quantity": 1,
        "department": "pharmacy",
        "unit": "30ML",
        "mrp": 99,
        "cgst": 0,
        "cgst_type": null,
        "sgst": 0,
        "sgst_type": null,
        "gst": 12,
        "gst_type": "PERCENT"
      },
      {
        "service": "ELECTRAL - APPLE FLAVOR",
        "amount": 58.8,
        "quantity": 2,
        "department": "pharmacy",
        "unit": "200ML",
        "mrp": 29.4,
        "cgst": 0,
        "cgst_type": null,
        "sgst": 0,
        "sgst_type": null,
        "gst": 5,
        "gst_type": "PERCENT"
      },
      {
        "service": "ELECTRAL - APPLE FLAVOR",
        "amount": 63,
        "quantity": 2,
        "department": "pharmacy",
        "unit": "200ML",
        "mrp": 31.5,
        "cgst": 0,
        "cgst_type": null,
        "sgst": 0,
        "sgst_type": null,
        "gst": 5,
        "gst_type": "PERCENT"
      }
    ],
    "total_amount": 824,
    "doctor_name": "ANIL ARORA",
    "facility": "SANTOSH MEDICOSE A-7, SHOP NO.1, EAST UTTAM NAGAR, HANUMAN MKT NEW DELHI-59. Ph. 9818890860",
    "invoice_date": "27/05/2024",
    "payment_mode": "Cash",
    "patient_age": null,
    "patient_gender": null,
    "patient_contact": null,
    "cgst": 40.52,
    "cgst_type": "AMOUNT",
    "sgst": 40.52,
    "sgst_type": "AMOUNT",
    "gst": 81.04,
    "gst_type": "AMOUNT",
    "discount": 0,
    "mrp": 0,
    "round_off": 0.08
  }
}