{
  "file_id": "e0bdd3c4_6775_49ab_96dc_9db4663bf6254324771919646368437",
  "raw_text": "=== CUSTOMER INFORMATION ===\nBill To: NIKHIL SANTHOSH NAIR\nGST: 7994938554\nBill To: NIKHIL SANTHOSH NAIR\n\n=== SUPPLIER INFORMATION ===\nADDRESS: WELLCAZA HOSPITAL PRIVATE LIMITED\nLFC Road, Puthiya Road Jn, kaloor Ernakulam-682017\nSTREET: LFC Road, Puthiya Road Jn,\nCITY: kaloor Ernakulam-682017\nNAME: WELLCAZA HOSPITAL PRIVATE LIMITED\nADDRESS_BLOCK: LFC Road, Puthiya Road Jn, kaloor Ernakulam-682017\nNAME: WELLCAZA MEDICITY\nGST :: 32AADCW4242J1ZF\nVENDOR_ADDRESS: WELLCAZA HOSPITAL PRIVATE LIMITED\nLFC Road, Puthiya Road Jn, kaloor Ernakulam-682017\nVENDOR_NAME: WELLCAZA HOSPITAL PRIVATE LIMITED\nVENDOR_NAME: WELLCAZA MEDICITY\nMobile:: 9995937876\nVENDOR_PHONE: 7907537824\n\n=== ADDITIONAL DOCUMENT DETAILS ===\n\nDiscount Amount: 0 Invoice Date :: 10/08/2024 Invoice No :: A/21109-0 GST :: 32AADCW4242J1ZF GST: 7994938554 Terms And Conditions: CASH\nRECEIVED Freight: 0 Total Amount Before Tax: 671.866 SUBTOTAL: 716.49 Add.CGST: 22.31 Add: SGST: 22.31 Add: IGST: 0 Tax Amount : GST: 44.62 Total Invoice Amount in words: Seven Hundred Sixteen Rupees only Net Amount: 716 Email :: welleaza@gmail.com State /Code :: Kerala-32 Bank Details: Bank Name:\nBank Branch :\nBank A/c No :\nBank Branch IFSC : S/\nN: 1 Item_Name: CASUALTY CONSULTATION Qty: 1.00 Price: 150.00 Disc: 0.00 Value: 150.00 %: 0.00 CGST: 0.00 %: 0.00 SGST: 0.00 Total: 150.00  | S/\nN: 1\n2 Item_Name: DRESSING MEDIUM Qty: 1.00 Price: 150.00 Disc: 0.00 Value: 150.00 %: 0.00 CGST: 0.00 %: 0.00 SGST: 0,00 Total: 150.00  | S/\nN: 3 HSN: 30049099 Item_Name: CL MOX 625 Qty: 15.00 Price: 18.50 Disc: 0.00 Value: 247.77 %: 6.00 CGST: 14.87 %: 6.00 SGST: 14.87 Total: 277.50  | S/\nN: 4 HSN: 30049039 Item_Name: PENTALOC 40MG TAB Qty: 5.00 Price: 8.44 Disc: 0.00 Value: 37.68 %: 6.00 CGST: 2.26 %: 6.00 SGST: 2.26 Total: 42.20  | S/\nN: 5 HSN: 30049061 Item_Name: ACENEXT- SP TAB Qty: 6.00 Price: 9.84 Disc: 0.00 Value: 52.71 %: 6.00 CGST: 3.16 %: 6.00 SGST: 3.16 Total: 59.04  | S/\nN: 6 HSN: 3004 Item_Name: VITAPIC-C TAB Qty: 5.00 Price: 7.55 Disc: 0.00 Value: 33.71 %: 6.00 CGST: 2.02 %: 6.00 SGST: 2.02 Total: 37,75  | \n\nRaw Text Content:\nWELLCAZA MEDICITY\nWELLCAZA HOSPITAL PRIVATE LIMITED\nLFC Road, Puthiya Road Jn, kaloor Ernakulam-682017\nMobile: 9995937876 7907537824\nEmail : welleaza@gmail.com\nGST : 32AADCW4242J1ZF\nINVOICE\nBill To\nInvoice No : A/21109-0\nNIKHIL SANTHOSH NAIR\nInvoice Date : 10/08/2024\nTransporation :\nState /Code :Kerala-32\nKerala\nGST\n7994938554\nS/\nUOM\nQty\nPrice\nItem_Name\nDisc\nValue\n%\nCGST\n%\nSGST\nTotal\nHSN\nN\n1.00\nCASUALTY CONSULTATION\n150.00\n0.00\n150.00\n0.00\n0.00\n0.00\n0.00\n150.00\n1\n1.00\n2\nDRESSING MEDIUM\n150.00\n0.00\n150.00\n0.00\n0.00\n0.00\n0,00\n150.00\n3\n30049099\nCL MOX 625\n15.00\n18.50\n0.00\n247.77\n6.00\n14.87\n6.00\n14.87\n277.50\n5.00\n6.00\n2.26\n42.20\n4\n30049039\nPENTALOC 40MG TAB\n8.44\n0.00\n37.68\n6.00\n2.26\n5\n30049061\nACENEXT- SP TAB\n6.00\n9.84\n0.00\n52.71\n6.00\n3.16\n6.00\n3.16\n59.04\n6\n3004\nVITAPIC-C TAB\n5.00\n7.55\n0.00\n33.71\n6.00\n2.02\n6.00\n2.02\n37,75\n33\n0\n671.87\n716.49\nTotal Amount Before Tax\nTotal Invoice Amount in words\n671.866\nSeven Hundred Sixteen Rupees only\nAdd.CGST\n22.31\nAdd:SGST\n22.31\nBank Details\nAdd:IGST\n0\nBank Name:\nBank Branch :\nTax Amount :GST\n44.62\nBank A/c No :\nDiscount Amount\n0\nBank Branch IFSC :\nFreight\n0\nTerms And Conditions\nNet Amount\n716\nCASH RECEIVED\nCertified That the Particulars given above are true and correct.\nFor\nSS\n(Common Seal)\nHostitage\nAuthorised Signatory\nKALOOR",
  "gold": {
    "invoice_number": "A/21109-0",
    "patient_name": "NIKHIL SANTHOSH NAIR",
    "services": [
      {
        "service": "CASUALTY CONSULTATION",
        "amount": 150,
        "quantity": 1,
        "department": "consultation",
        "unit": null,
        "mrp": 150,
        "cgst": 0,
        "cgst_type": null,
        "sgst": 0,
        "sgst_type": null,
        "gst": 0,
        "gst_type": null
      },
      {
        "service": "DRESSING MEDIUM",
        "amount": 150,
        "quantity": 1,
        "department": "medical",
        "unit": null,
        "mrp": 150,
        "cgst": 0,
        "cgst_type": null,
        "sgst": 0,
        "sgst_type": null,
        "gst": 0,
        "gst_type": null
      },
      {
        "service": "CL MOX 625",
        "amount": 277.5,
        "quantity": 15,
        "department": "pharmacy",
        "unit": null,
        "mrp": 18.5,
        "cgst": 14.87,
        "cgst_type": "AMOUNT",
        "sgst": 14.87,
        "sgst_type": "AMOUNT",
        "gst": 6,
        "gst_type": "PERCENT"
      },
      {
        "service": "PENTALOC 40MG TAB",
        "amount": 42.2,
        "quantity": 5,
        "department": "pharmacy",
        "unit": "TAB",
        "mrp": 8.44,
        "cgst": 2.26,
        "cgst_type": "AMOUNT",
        "sgst": 2.26,
        "sgst_type": "AMOUNT",
        "gst": 6,
        "gst_type": "PERCENT"
      },
      {
        "service": "ACENEXT- SP TAB",
        "amount": 59.04,
        "quantity": 6,
        "department": "pharmacy",
        "unit": "TAB",
        "mrp": 9.84,
        "cgst": 3.16,
        "cgst_type": "AMOUNT",
        "sgst": 3.16,
        "sgst_type": "AMOUNT",
        "gst": 6,
        "gst_type": "PERCENT"
      },
      {
        "service": "VITAPIC-C TAB",
        "amount": 37.75,
        "quantity": 5,
        "department": "pharmacy",
        "unit": "TAB",
        "mrp": 7.55,
        "cgst": 2.02,
        "cgst_type": "AMOUNT",
        "sgst": 2.02,
        "sgst_type": "AMOUNT",
        "gst": 6,
        "gst_type": "PERCENT"
      }
    ],
    "total_amount": 716,
    "doctor_name": null,
    "facility": "WELLCAZA HOSPITAL PRIVATE LIMITED, LFC Road, Puthiya Road Jn, kaloor Ernakulam-682017, Mobile: 9995937876 7907537824",
    "invoice_date": "10/08/2024",
    "payment_mode": "CASH",
    "patient_age": null,
    "patient_gender": null,
    "patient_contact": "7994938554",
    "cgst": 22.31,
    "cgst_type": "AMOUNT",
    "sgst": 22.31,
    "sgst_type": "AMOUNT",
    "gst": 44.62,
    "gst_type": "AMOUNT",
    "discount": 0,
    "mrp": 671.87,
    "round_off": 0
  }
}