{
  "file_id": "image_picker_50F21DC6_A227_4614_A76B_8CFA5E181FCB_11769_000001FA59BA8A8B",
  "raw_text": "=== CUSTOMER INFORMATION ===\nBill To: K SEBASTIAN\nBill To: K SEBASTIAN\n\n=== SUPPLIER INFORMATION ===\nNAME: VR CHEST AND WOMEN CARE\nNAME: VR CHEST AND WOMEN CARE\nVENDOR_NAME: VR CHEST AND WOMEN CARE\nVENDOR_NAME: VR CHEST AND WOMEN CARE\nPhone no.:: 9742532343\n\n=== ADDITIONAL DOCUMENT DETAILS ===\n\nReceived: ₹ 4,059.00 You Saved: ₹ 204.10 Date: 02-10-2024 Invoice No. :: 104242424 Total: 4,058.90 Sub Total: 4,058.90 Total: 4,059.00 Invoice Amount In Words: Four Thousand Fifty Nine Rupees only Email:: VRCHESTANDWOMENCARE@GMAILCOM State:: 29-Karnataka KMC:: 87920 GENDER: M Model No.:: 30049099 Model No.:: 30049091 Model No.:: 30049099 Model No.:: 90192090 Model No.:: 30022019 Amounts: Sub Total\n4,058.90\nRound off\n₹0,10\nTotal\n4,059.00\nReceived Round off: ₹0,10 Balance: 0.00 erms and Conditions: anks for doing business with us! KMC: 87920  |  |  |  |  | \n\nRaw Text Content:\nTax Invoice\nVR CHEST AND WOMEN CARE\nGround floor, Elegant habitat building, Hennur Main Rd, behind Skechers\nshowroom, Byreshwara Layout, Hennur Bande, Kalyan Nagar, Bengaluru, Karnataka\n560043\nPhone no.: 9742532343 Email: VRCHESTANDWOMENCARE@GMAILCOM\nState: 29-Karnataka\nKMC: 87920\nBill To\nInvoice Details\nK SEBASTIAN\nInvoice No. : 104242424\nDate 02-10-2024\nGENDER M\nItem name\nHSN/ SAC\nBatch No.\nExp.\nDate\nMRP\nQuantity\nUnit\nPrice/ Unit\nDiscount\nAmount\nMONTE- FX\nModel No.: 30049099\n2404078\n₹ 21.80\n30\n65.40\n-\n21.80\n588.60\n(10%)\nAIRZ-FB INH\n63240007\nModel No.: 30049091\n11/2025\n820.00\n1\n82.00\nINH\n820.00\n738.00\n(10%)\nBILATEZ 20 TAB\nModel No.: 30049099\nUGT231175\n08/2025\n11.80\n15\n17.70\n-\n11.80\n159.30\n(10%)\nPEARL SPACER\nPRLSPCR-\nModel No.: 90192090\n09\n05/2027\n390.00\n1\n39.00\n-\n₹ 390.00\n₹ 351.00\n(10%)\nINFLUVAC TETRA SH 2024\nH23\nModel No.: 30022019\n01/2025\n2,222.00\n1\n-\n2,222.00\n₹0.00 (0%)\n2,222.00\nTotal\n48\n₹204.10\n4,058.90\nAmounts\nSub Total\n4,058.90\nRound off\n₹0,10\nTotal\n4,059.00\nReceived\n₹ 4,059.00\nBalance\n0.00\nYou Saved\n₹ 204.10\nInvoice Amount In Words\nFour Thousand Fifty Nine Rupees only\nerms and Conditions\nFor VR CHEST AND WOMEN CARE\nanks for doing business with us!\nto\nDr. Authorized Signatory\nVASUNE\nMBBS, MD, EDRM (FRAN\nCONSULTANT PULMONOLOG.ST\nKMC 87920",
  "gold": {
    "invoice_number": "104242424",
    "patient_name": "K C SEBASTIAN",
    "services": [
      {
        "service": "MONTE- FX",
        "amount": 588.6,
        "quantity": 30,
        "department": "pharmacy",
        "unit": "",
        "mrp": 21.8,
        "cgst": 0,
        "cgst_type": null,
        "sgst": 0,
        "sgst_type": null,
        "gst": 0,
        "gst_type": null
      },
      {
        "service": "AIRZ-FB INH",
        "amount": 738,
        "quantity": 1,
        "department": "pharmacy",
        "unit": "INH",
        "mrp": 820,
        "cgst": 0,
        "cgst_type": null,
        "sgst": 0,
        "sgst_type": null,
        "gst": 0,
        "gst_type": null
      },
      {
        "service": "BILATEZ 20 TAB",
        "amount": 159.3,
        "quantity": 15,
        "department": "pharmacy",
        "unit": "",
        "mrp": 11.8,
        "cgst": 0,
        "cgst_type": null,
        "sgst": 0,
        "sgst_type": null,
        "gst": 0,
        "gst_type": null
      },
      {
        "service": "PEARL SPACER",
        "amount": 351,
        "quantity": 1,
        "department": "pharmacy",
        "unit": "",
        "mrp": 390,
        "cgst": 0,
        "cgst_type": null,
        "sgst": 0,
        "sgst_type": null,
        "gst": 0,
        "gst_type": null
      },
      {
        "service": "INFLUVAC TETRA SH 2024",
        "amount": 2222,
        "quantity": 1,
        "department": "pharmacy",
        "unit": "",
        "mrp": 2222,
        "cgst": 0,
        "cgst_type": null,
        "sgst": 0,
        "sgst_type": null,
        "gst": 0,
        "gst_type": null
      }
    ],
    "total_amount": 4059,
    "doctor_name": "Dr. VASUNE",
    "facility": "VR CHEST AND WOMEN CARE, Ground floor, Elegant habitat building, Hennur Main Rd, behind Skechers showroom, Byreshwara Layout, Hennur Bande, Kalyan Nagar, Bengaluru, Karnataka 560043, Phone no.: 9742532343",
    "invoice_date": "02-10-2024",
    "payment_mode": null,
    "patient_age": null,
    "patient_gender": "Male",
    "patient_contact": null,
    "cgst": 0,
    "cgst_type": null,
    "sgst": 0,
    "sgst_type": null,
    "gst": 0,
    "gst_type": null,
    "discount": 204.1,
    "mrp": 0,
    "round_off": 0.1
  }
}